sqlalchemy_dev_utils-1.3.1.dist-info/METADATA
sqlalchemy_dev_utils-1.3.1.dist-info/WHEEL
sqlalchemy_dev_utils-1.3.1.dist-info/entry_points.txt
sqlalchemy_dev_utils-1.3.1.dist-info/licenses/LICENSE
sqlalchemy_dev_utils/__init__.py
sqlalchemy_dev_utils/alembic/__init__.py
sqlalchemy_dev_utils/alembic/ignore_table.py
sqlalchemy_dev_utils/alembic/migration_numbering.py
sqlalchemy_dev_utils/alembic/utils.py
sqlalchemy_dev_utils/exc.py
sqlalchemy_dev_utils/guards.py
sqlalchemy_dev_utils/mixins/__init__.py
sqlalchemy_dev_utils/mixins/audit.py
sqlalchemy_dev_utils/mixins/base.py
sqlalchemy_dev_utils/mixins/general.py
sqlalchemy_dev_utils/mixins/ids.py
sqlalchemy_dev_utils/naming_conventions.py
sqlalchemy_dev_utils/py.typed
sqlalchemy_dev_utils/types/__init__.py
sqlalchemy_dev_utils/types/datetime.py
sqlalchemy_dev_utils/types/pydantic.py
sqlalchemy_dev_utils/types/relativedelta.py
sqlalchemy_dev_utils/utils.py
sqlalchemy_dev_utils-1.3.1.dist-info/RECORD
