Metadata-Version: 2.1
Name: sqlalchemy_dev_utils
Version: 1.3.1
Summary: My sqlalchemy utils package, that I use in my projects.
Author-Email: Dmitriy Lunev <dima.lunev14@gmail.com>
License: MIT
Requires-Python: >=3.11
Requires-Dist: sqlalchemy>=2.0
Requires-Dist: python-dev-utils==7.0.1
Provides-Extra: pydantic-field
Requires-Dist: pydantic; extra == "pydantic-field"
Provides-Extra: relativedelta-field
Requires-Dist: python-dateutil; extra == "relativedelta-field"
Provides-Extra: alembic
Requires-Dist: alembic; extra == "alembic"
